cklearn/__init__.py
ck_learn-0.0.1.dist-info/METADATA
ck_learn-0.0.1.dist-info/WHEEL
ck_learn-0.0.1.dist-info/top_level.txt
ck_learn-0.0.1.dist-info/RECORD
